{
  "id": "SEC-020",
  "category": "security",
  "title": "Intrusion Detection System (IDS) Rule Matcher",
  "description": "Reads Snort-like rules from stdin, then reads network packet summaries and checks them against the rules. Reports matches with rule ID, severity, and description.",
  "difficulty": 4,
  "stdlib_modules": [
    "std.str",
    "std.json",
    "std.net"
  ],
  "repair_count": 3,
  "one_shot": false,
  "toke_api_compiled": false,
  "warnings": [],
  "generated_at": "2026-06-01T01:13:54.807483+00:00",
  "worker_id": 2,
  "source_chars": 796,
  "source_lines": 1,
  "has_companion": true,
  "has_repair_pairs": true,
  "test_cases_count": 2
}