{
  "id": "SYS-054",
  "category": "system-tools",
  "title": "Clipboard Manager (stdout)",
  "description": "Read clipboard content, print it, or set clipboard from stdin.",
  "difficulty": 2,
  "stdlib_modules": [
    "std.process",
    "std.io"
  ],
  "repair_count": 1,
  "one_shot": false,
  "toke_api_compiled": false,
  "warnings": [],
  "generated_at": "2026-06-01T01:34:57.559231+00:00",
  "worker_id": 3,
  "source_chars": 152,
  "source_lines": 1,
  "has_companion": true,
  "has_repair_pairs": true,
  "test_cases_count": 2
}