{
  "id": "CRY-040",
  "category": "crypto-blockchain",
  "title": "BIP39 Mnemonic to Seed",
  "description": "Read a mnemonic phrase and optional passphrase. Output the 64-byte BIP39 seed as hex.",
  "difficulty": 4,
  "stdlib_modules": [
    "std.crypto",
    "std.io",
    "std.encoding"
  ],
  "repair_count": 2,
  "one_shot": false,
  "toke_api_compiled": false,
  "warnings": [],
  "generated_at": "2026-06-01T00:47:36.676949+00:00",
  "worker_id": 3,
  "source_chars": 437,
  "source_lines": 1,
  "has_companion": true,
  "has_repair_pairs": true,
  "test_cases_count": 2
}